{
  "provider_arguments": [],
  "resources": {
    "log": {
      "arguments": [
        {
          "word": "filename",
          "kind": "String(O)",
          "type": "string",
          "block": false,
          "required": true
        },
        {
          "word": "logset_id",
          "kind": "String(R)",
          "type": "string",
          "block": false,
          "required": false
        },
        {
          "word": "name",
          "kind": "String(R)",
          "type": "string",
          "block": false,
          "required": false
        },
        {
          "word": "retention_period",
          "kind": "String(O)",
          "type": "string",
          "block": false,
          "required": true
        },
        {
          "word": "source",
          "kind": "String(O)",
          "type": "string",
          "block": false,
          "required": true
        },
        {
          "word": "type",
          "kind": "String(O)",
          "type": "string",
          "block": false,
          "required": true
        }
      ],
      "attributes": [
        {
          "word": "token",
          "kind": "String",
          "type": "string",
          "block": false
        },
        {
          "word": "id",
          "kind": "String",
          "type": "string",
          "block": false
        }
      ]
    },
    "logset": {
      "arguments": [
        {
          "word": "location",
          "kind": "String(O)",
          "type": "string",
          "block": false,
          "required": true
        },
        {
          "word": "name",
          "kind": "String(R)",
          "type": "string",
          "block": false,
          "required": false
        }
      ],
      "attributes": [
        {
          "word": "id",
          "kind": "String",
          "type": "string",
          "block": false
        }
      ]
    }
  },
  "datas": {},
  "unknowns": {},
  "__meta": {
    "type": "provider"
  }
}